{
  "kind": "books#volumes",
  "totalItems": 982,
  "items": [
    {
      "kind": "books#volume",
      "id": "B8aehjSIZkgC",
      "etag": "kU1WH0RQyTk",
      "selfLink": "https://www.googleapis.com/books/v1/volumes/B8aehjSIZkgC",
      "volumeInfo": {
        "title": "Attacking Soccer",
        "subtitle": "Mastering the Modern Game",
        "authors": [
          "Peter Schreiner",
          "Norbert Elgert"
        ],
        "publisher": "Meyer & Meyer Verlag",
        "publishedDate": "2013",
        "description": "Soccer fans around the world adore the offensive style of play based on fast passing combinations, spectacular dribblings, and the art of beautifully shot goals. The question regarding this style of game is how to coach your team to embrace fast attacking soccer. How do you shape your training to cover all the technical and tactical basics? Peter ......",
        "industryIdentifiers": [
          {
            "type": "ISBN_13",
            "identifier": "9781782550082"
          },
          {
            "type": "ISBN_10",
            "identifier": "1782550089"
          }
        ],
        "readingModes": {
          "text": false,
          "image": true
        },
        "pageCount": 170,
        "printType": "BOOK",
        "categories": [
          "Sports & Recreation"
        ],
        "averageRating": 5,
        "ratingsCount": 1,
        "maturityRating": "NOT_MATURE",
        "allowAnonLogging": false,
        "contentVersion": "0.1.1.0.preview.1",
        "panelizationSummary": {
          "containsEpubBubbles": false,
          "containsImageBubbles": false
        },
        "imageLinks": {
          "smallThumbnail": "http://books.google.com/books/content?id=B8aehjSIZkgC&printsec=frontcover&img=1&zoom=5&edge=curl&source=gbs_api",
          "thumbnail": "http://books.google.com/books/content?id=B8aehjSIZkgC&printsec=frontcover&img=1&zoom=1&edge=curl&source=gbs_api"
        },
        "language": "en",
        "previewLink": "http://books.google.com.vn/books?id=B8aehjSIZkgC&pg=PA15&dq=Attack&hl=&cd=1&source=gbs_api",
        "infoLink": "http://books.google.com.vn/books?id=B8aehjSIZkgC&dq=Attack&hl=&source=gbs_api",
        "canonicalVolumeLink": "https://books.google.com/books/about/Attacking_Soccer.html?hl=&id=B8aehjSIZkgC"
      },
      "saleInfo": {
        "country": "VN",
        "saleability": "NOT_FOR_SALE",
        "isEbook": false
      },
      "accessInfo": {
        "country": "VN",
        "viewability": "PARTIAL",
        "embeddable": true,
        "publicDomain": false,
        "textToSpeechPermission": "ALLOWED",
        "epub": {
          "isAvailable": false
        },
        "pdf": {
          "isAvailable": true,
          "acsTokenLink": "http://books.google.com.vn/books/download/Attacking_Soccer-sample-pdf.acsm?id=B8aehjSIZkgC&format=pdf&output=acs4_fulfillment_token&dl_type=sample&source=gbs_api"
        },
        "webReaderLink": "http://play.google.com/books/reader?id=B8aehjSIZkgC&hl=&source=gbs_api",
        "accessViewStatus": "SAMPLE",
        "quoteSharingAllowed": false
      },
      "searchInfo": {
        "textSnippet": "... \u003cb\u003eattack\u003c/b\u003e mentality always anticipate the possibility of a counter \u003cb\u003eattack\u003c/b\u003e and are prepared to quickly switch to \u003cb\u003eattack\u003c/b\u003e mode after gaining possession of the ball . All players keep constant track of the game and know the exact location of&nbsp;..."
      }
    },
    {
      "kind": "books#volume",
      "id": "tUAOSknl6WYC",
      "etag": "cv6xmjIHe2k",
      "selfLink": "https://www.googleapis.com/books/v1/volumes/tUAOSknl6WYC",
      "volumeInfo": {
        "title": "Military Dictionary",
        "subtitle": "(advance Installment) Part. I. English-Portuguese. Part II. Portuguese-English",
        "authors": [
          "United States. War Department. Military Dictionary Project"
        ],
        "publishedDate": "1941",
        "industryIdentifiers": [
          {
            "type": "OTHER",
            "identifier": "WISC:89090038779"
          }
        ],
        "readingModes": {
          "text": false,
          "image": true
        },
        "pageCount": 396,
        "printType": "BOOK",
        "categories": [
          "English language"
        ],
        "maturityRating": "NOT_MATURE",
        "allowAnonLogging": false,
        "contentVersion": "1.4.5.0.full.1",
        "panelizationSummary": {
          "containsEpubBubbles": false,
          "containsImageBubbles": false
        },
        "imageLinks": {
          "smallThumbnail": "http://books.google.com/books/content?id=tUAOSknl6WYC&printsec=frontcover&img=1&zoom=5&edge=curl&source=gbs_api",
          "thumbnail": "http://books.google.com/books/content?id=tUAOSknl6WYC&printsec=frontcover&img=1&zoom=1&edge=curl&source=gbs_api"
        },
        "language": "en",
        "previewLink": "http://books.google.com.vn/books?id=tUAOSknl6WYC&pg=PA14&dq=Attack&hl=&cd=2&source=gbs_api",
        "infoLink": "https://play.google.com/store/books/details?id=tUAOSknl6WYC&source=gbs_api",
        "canonicalVolumeLink": "https://play.google.com/store/books/details?id=tUAOSknl6WYC"
      },
      "saleInfo": {
        "country": "VN",
        "saleability": "FREE",
        "isEbook": true,
        "buyLink": "https://play.google.com/store/books/details?id=tUAOSknl6WYC&rdid=book-tUAOSknl6WYC&rdot=1&source=gbs_api"
      },
      "accessInfo": {
        "country": "VN",
        "viewability": "ALL_PAGES",
        "embeddable": true,
        "publicDomain": true,
        "textToSpeechPermission": "ALLOWED",
        "epub": {
          "isAvailable": false,
          "downloadLink": "http://books.google.com.vn/books/download/Military_Dictionary.epub?id=tUAOSknl6WYC&hl=&output=epub&source=gbs_api"
        },
        "pdf": {
          "isAvailable": false
        },
        "webReaderLink": "http://play.google.com/books/reader?id=tUAOSknl6WYC&hl=&source=gbs_api",
        "accessViewStatus": "FULL_PUBLIC_DOMAIN",
        "quoteSharingAllowed": false
      },
      "searchInfo": {
        "textSnippet": "... \u003cb\u003eattack\u003c/b\u003e formations ataque . \u003cb\u003eattack\u003c/b\u003e from above \u003cb\u003eattack\u003c/b\u003e from below baixo . \u003cb\u003eattack\u003c/b\u003e from the air \u003cb\u003eattack\u003c/b\u003e from the rear retaguarda . \u003cb\u003eattack\u003c/b\u003e frontage formações de ataque de cima . ataque de boundaries in the \u003cb\u003eattack\u003c/b\u003e do ataque . ataque do ar&nbsp;..."
      }
    },
    {
      "kind": "books#volume",
      "id": "X374DwAAQBAJ",
      "etag": "O8VV/29GrcA",
      "selfLink": "https://www.googleapis.com/books/v1/volumes/X374DwAAQBAJ",
      "volumeInfo": {
        "title": "Computer Safety, Reliability, and Security",
        "subtitle": "39th International Conference, SAFECOMP 2020, Lisbon, Portugal, September 16–18, 2020, Proceedings",
        "authors": [
          "António Casimiro",
          "Frank Ortmeier",
          "Friedemann Bitsch",
          "Pedro Ferreira"
        ],
        "publisher": "Springer Nature",
        "publishedDate": "2020-08-19",
        "description": "This book constitutes the proceedings of the 39th International Conference on Computer Safety, Reliability and Security, SAFECOMP 2020, held in Lisbon, Portugal, in September 2020.* The 27 full and 2 short papers included in this volume were carefully reviewed and selected from 116 submissions. They were organized in topical sections named: safety cases and argumentation; formal verification and analysis; security modelling and methods; assurance of learning-enabled systems; practical experience and tools; threat analysis and risk mitigation; cyber-physical systems security; and fault injection and fault tolerance. *The conference was held virtually due to the COVID-19 pandemic. The chapter ‘Assurance Argument Elements for Off-the-Shelf, Complex Computational Hardware’ is available open access under an Open Government License 3.0 via link.springer.com.",
        "industryIdentifiers": [
          {
            "type": "ISBN_13",
            "identifier": "9783030545499"
          },
          {
            "type": "ISBN_10",
            "identifier": "3030545490"
          }
        ],
        "readingModes": {
          "text": true,
          "image": true
        },
        "pageCount": 460,
        "printType": "BOOK",
        "categories": [
          "Computers"
        ],
        "maturityRating": "NOT_MATURE",
        "allowAnonLogging": false,
        "contentVersion": "0.2.2.0.preview.3",
        "panelizationSummary": {
          "containsEpubBubbles": false,
          "containsImageBubbles": false
        },
        "imageLinks": {
          "smallThumbnail": "http://books.google.com/books/content?id=X374DwAAQBAJ&printsec=frontcover&img=1&zoom=5&edge=curl&source=gbs_api",
          "thumbnail": "http://books.google.com/books/content?id=X374DwAAQBAJ&printsec=frontcover&img=1&zoom=1&edge=curl&source=gbs_api"
        },
        "language": "en",
        "previewLink": "http://books.google.com.vn/books?id=X374DwAAQBAJ&pg=PA345&dq=Attack&hl=&cd=3&source=gbs_api",
        "infoLink": "https://play.google.com/store/books/details?id=X374DwAAQBAJ&source=gbs_api",
        "canonicalVolumeLink": "https://play.google.com/store/books/details?id=X374DwAAQBAJ"
      },
      "saleInfo": {
        "country": "VN",
        "saleability": "FOR_SALE",
        "isEbook": true,
        "listPrice": {
          "amount": 2447705,
          "currencyCode": "VND"
        },
        "retailPrice": {
          "amount": 1713394,
          "currencyCode": "VND"
        },
        "buyLink": "https://play.google.com/store/books/details?id=X374DwAAQBAJ&rdid=book-X374DwAAQBAJ&rdot=1&source=gbs_api",
        "offers": [
          {
            "finskyOfferType": 1,
            "listPrice": {
              "amountInMicros": 2447705000000,
              "currencyCode": "VND"
            },
            "retailPrice": {
              "amountInMicros": 1713394000000,
              "currencyCode": "VND"
            }
          }
        ]
      },
      "accessInfo": {
        "country": "VN",
        "viewability": "PARTIAL",
        "embeddable": true,
        "publicDomain": false,
        "textToSpeechPermission": "ALLOWED",
        "epub": {
          "isAvailable": true,
          "acsTokenLink": "http://books.google.com.vn/books/download/Computer_Safety_Reliability_and_Security-sample-epub.acsm?id=X374DwAAQBAJ&format=epub&output=acs4_fulfillment_token&dl_type=sample&source=gbs_api"
        },
        "pdf": {
          "isAvailable": true,
          "acsTokenLink": "http://books.google.com.vn/books/download/Computer_Safety_Reliability_and_Security-sample-pdf.acsm?id=X374DwAAQBAJ&format=pdf&output=acs4_fulfillment_token&dl_type=sample&source=gbs_api"
        },
        "webReaderLink": "http://play.google.com/books/reader?id=X374DwAAQBAJ&hl=&source=gbs_api",
        "accessViewStatus": "SAMPLE",
        "quoteSharingAllowed": false
      },
      "searchInfo": {
        "textSnippet": "... \u003cb\u003eattack\u003c/b\u003e &quot; is to analyze the &quot; Trust Boundary &quot; , which specifies the area of protection from \u003cb\u003eattacks\u003c/b\u003e in the entire system architecture . The fourth criterion &quot; How does an \u003cb\u003eattack\u003c/b\u003e reach the target &quot; is to analyze the &quot; \u003cb\u003eAttack\u003c/b\u003e Path &quot; which&nbsp;..."
      }
    },
    {
      "kind": "books#volume",
      "id": "OG-hBQAAQBAJ",
      "etag": "JZhp7YBFfrk",
      "selfLink": "https://www.googleapis.com/books/v1/volumes/OG-hBQAAQBAJ",
      "volumeInfo": {
        "title": "Computer Science and its Applications",
        "subtitle": "Ubiquitous Information Technologies",
        "authors": [
          "James J. (Jong Hyuk) Park",
          "Ivan Stojmenovic",
          "Hwa Young Jeong",
          "Gangman Yi"
        ],
        "publisher": "Springer",
        "publishedDate": "2014-11-29",
        "description": "The 6th FTRA International Conference on Computer Science and its Applications (CSA-14) will be held in Guam, USA, Dec. 17 - 19, 2014. CSA-14 presents a comprehensive conference focused on the various aspects of advances in engineering systems in computer science, and applications, including ubiquitous computing, U-Health care system, Big Data, UI/UX for human-centric computing, Computing Service, Bioinformatics and Bio-Inspired Computing and will show recent advances on various aspects of computing technology, Ubiquitous Computing Services and its application.",
        "industryIdentifiers": [
          {
            "type": "ISBN_13",
            "identifier": "9783662454022"
          },
          {
            "type": "ISBN_10",
            "identifier": "3662454025"
          }
        ],
        "readingModes": {
          "text": false,
          "image": true
        },
        "pageCount": 1395,
        "printType": "BOOK",
        "categories": [
          "Technology & Engineering"
        ],
        "maturityRating": "NOT_MATURE",
        "allowAnonLogging": false,
        "contentVersion": "0.1.1.0.preview.1",
        "panelizationSummary": {
          "containsEpubBubbles": false,
          "containsImageBubbles": false
        },
        "imageLinks": {
          "smallThumbnail": "http://books.google.com/books/content?id=OG-hBQAAQBAJ&printsec=frontcover&img=1&zoom=5&edge=curl&source=gbs_api",
          "thumbnail": "http://books.google.com/books/content?id=OG-hBQAAQBAJ&printsec=frontcover&img=1&zoom=1&edge=curl&source=gbs_api"
        },
        "language": "en",
        "previewLink": "http://books.google.com.vn/books?id=OG-hBQAAQBAJ&pg=PA513&dq=Attack&hl=&cd=4&source=gbs_api",
        "infoLink": "https://play.google.com/store/books/details?id=OG-hBQAAQBAJ&source=gbs_api",
        "canonicalVolumeLink": "https://play.google.com/store/books/details?id=OG-hBQAAQBAJ"
      },
      "saleInfo": {
        "country": "VN",
        "saleability": "FOR_SALE",
        "isEbook": true,
        "listPrice": {
          "amount": 8323130,
          "currencyCode": "VND"
        },
        "retailPrice": {
          "amount": 5826191,
          "currencyCode": "VND"
        },
        "buyLink": "https://play.google.com/store/books/details?id=OG-hBQAAQBAJ&rdid=book-OG-hBQAAQBAJ&rdot=1&source=gbs_api",
        "offers": [
          {
            "finskyOfferType": 1,
            "listPrice": {
              "amountInMicros": 8323130000000,
              "currencyCode": "VND"
            },
            "retailPrice": {
              "amountInMicros": 5826191000000,
              "currencyCode": "VND"
            }
          }
        ]
      },
      "accessInfo": {
        "country": "VN",
        "viewability": "PARTIAL",
        "embeddable": true,
        "publicDomain": false,
        "textToSpeechPermission": "ALLOWED",
        "epub": {
          "isAvailable": false
        },
        "pdf": {
          "isAvailable": true,
          "acsTokenLink": "http://books.google.com.vn/books/download/Computer_Science_and_its_Applications-sample-pdf.acsm?id=OG-hBQAAQBAJ&format=pdf&output=acs4_fulfillment_token&dl_type=sample&source=gbs_api"
        },
        "webReaderLink": "http://play.google.com/books/reader?id=OG-hBQAAQBAJ&hl=&source=gbs_api",
        "accessViewStatus": "SAMPLE",
        "quoteSharingAllowed": false
      },
      "searchInfo": {
        "textSnippet": "... \u003cb\u003eAttack\u003c/b\u003e 2.1 Least demanding \u003cb\u003eattacks\u003c/b\u003e are the most serious threats to the hardware security of any device, because this type of \u003cb\u003eattack\u003c/b\u003e requires ... \u003cb\u003eattack\u003c/b\u003e chips. One \u003cb\u003eattack\u003c/b\u003e chip Quantifying Overt Hardware \u003cb\u003eAttacks\u003c/b\u003e: Using ART Schema 513."
      }
    }
  ]
}
